flyte_provider/__init__.py
flyte_provider/hooks/__init__.py
flyte_provider/hooks/flyte.py
flyte_provider/operators/__init__.py
flyte_provider/operators/flyte.py
flyte_provider/sensors/__init__.py
flyte_provider/sensors/flyte.py
airflow_provider_flyte-0.0.5.dist-info/LICENSE
airflow_provider_flyte-0.0.5.dist-info/METADATA
airflow_provider_flyte-0.0.5.dist-info/WHEEL
airflow_provider_flyte-0.0.5.dist-info/entry_points.txt
airflow_provider_flyte-0.0.5.dist-info/top_level.txt
airflow_provider_flyte-0.0.5.dist-info/RECORD
