Metadata-Version: 2.1
Name: airflow-provider-flyte
Version: 0.0.5
Summary: Flyte Airflow Provider
Home-page: https://flyte.org/
Author: Samhita Alla
Author-email: samhita@union.ai
License: Apache License 2.0
Platform: UNKNOWN
Classifier: Framework :: Apache Airflow
Classifier: Framework :: Apache Airflow :: Provider
Requires-Python: ~=3.7
License-File: LICENSE
Requires-Dist: apache-airflow (>=2.0)
Requires-Dist: flytekit (>=1.0.0)
